moat/db/thing/__init__.py
moat/db/thing/_main.py
moat/db/thing/model.py
moat/db/thing/model_.py
moat/thing/__init__.py
moat/thing/_main.py
moat/thing/model.py
moat/thing/model_.py
moat_db_thing-0.0.2.dist-info/licenses/LICENSE.txt
moat_db_thing-0.0.2.dist-info/METADATA
moat_db_thing-0.0.2.dist-info/WHEEL
moat_db_thing-0.0.2.dist-info/top_level.txt
moat_db_thing-0.0.2.dist-info/RECORD
