Metadata-Version: 2.4
Name: moat-db-thing
Version: 0.0.2
Summary: MoaT support for storing info about things
Author-email: Matthias Urlichs <matthias@urlichs.de>
Project-URL: homepage, https://m-o-a-t.org
Project-URL: repository, https://github.com/M-o-a-T/moat
Keywords: MoaT
Classifier: Intended Audience :: Developers
Classifier: Programming Language :: Python :: 3
Classifier: Framework :: AsyncIO
Classifier: Framework :: Trio
Classifier: Framework :: AnyIO
Classifier: Development Status :: 4 - Beta
Requires-Python: >=3.8
License-File: LICENSE.txt
Requires-Dist: anyio~=4.2
Requires-Dist: asyncclick
Requires-Dist: attrs
Requires-Dist: msgpack
Requires-Dist: moat-util~=0.61.1
Requires-Dist: moat-db~=0.2.5
Requires-Dist: moat-label~=0.2.2
Requires-Dist: moat-box~=0.2.2
Requires-Dist: moat-lib-run~=0.1.0
Dynamic: license-file
